rtl/alu.sv
//alu.sv
//basic arithmetic logic 
`timescale 1ns/1ps

module alu(
    input   logic[31:0] a, b,
    input   cpu_defs::AluOp  alu_op,
    output  logic[31:0] result
);
    import cpu_defs::*;

    always_comb begin : alu_logic
        case(alu_op)
            ALU_ADD: result = a + b; 
            ALU_SUB: result = a - b; 
            ALU_AND: result = a & b; 
            ALU_OR: result = a | b; 
            ALU_XOR: result = a ^ b; 
            ALU_SLL: result = a << b[4:0]; //SLL shift left logical, mask b since a is 32 bit and should only be shifted by max 31 bit
            ALU_SRL: result = a >> b[4:0]; //SRL shift right logical
            ALU_SLT: result = ($signed(a) < $signed(b)) ? 32'd1 : 32'd0; //SLT set less than (signed) (condition) ? value_if_true : value_if_false
            ALU_SLTU: result = (a < b) ? 32'd1 : 32'd0; //SLT set less than unsigned
            default: result = 32'd0; 
        endcase
    end

endmodule

tb/tb_alu.sv
//tb_alu.sv
//testbench for alu.sv

`timescale 1ns/1ps //time unit/time precision

module tb_alu;

    //inputs
    logic[31:0] a, b;
    cpu_defs::AluOp       alu_op;

    //output
    logic[31:0] result;

    //instantiate alu
    alu uut (
        .a(a),
        .b(b),
        .alu_op(alu_op),
        .result(result)
    );

    import cpu_defs::*;

    

    initial begin
        $dumpfile("tb_alu.vcd"); //name output vcd
        $dumpvars(0, tb_alu); //dump everything recursively
    end

    //testing 
    initial begin
        $display("=== ALU Unit Test ===");
        a = 10; b = 5; 

        alu_op = ALU_ADD;
        #1;
        $display("ADD: %0d + %0d = %0d", a, b, result);

        alu_op = ALU_SUB;
        #1;
        $display("SUB: %0d - %0d = %0d", a, b, result);

        alu_op = ALU_AND;
        #1;
        $display("AND: b%04b & b%04b = b%04b", a, b, result);

        alu_op = ALU_OR;
        #1;
        $display("OR: b%04b | b%04b = b%04b", a, b, result);

        alu_op = ALU_XOR;
        #1;
        $display("XOR: b%04b ^ b%04b = b%04b", a, b, result);

        alu_op = ALU_SLL;
        #1;
        $display("SLL: b%04b << %0d = b%04b", a, b[4:0], result);

        alu_op = ALU_SRL;
        #1;
        $display("SRL: b%04b >> %0d = b%04b", a, b[4:0], result);

        a = -5; b = 3; 
        alu_op = ALU_SLT;
        #1;
        $display("SLT: %0d < %0d ? 1:0 = %0d", $signed(a), $signed(b), result);

        a = 32'hFFFFFFFF; b = 1; 
        alu_op = ALU_SLTU;
        #1;
        $display("SLTU: %0d < %0d ? 1:0 = %0d", a, b, result);

        $display("=== ALU Test Complete ===");
        $finish;
    end
endmodule

tb_alu.vcd
$version Generated by VerilatedVcd $end
$timescale 1ps $end
 $scope module tb_alu $end
  $var wire 32 # a [31:0] $end
  $var wire 32 $ b [31:0] $end
  $var wire 4 % alu_op [3:0] $end
  $var wire 32 & result [31:0] $end
  $scope module uut $end
   $var wire 32 # a [31:0] $end
   $var wire 32 $ b [31:0] $end
   $var wire 4 % alu_op [3:0] $end
   $var wire 32 & result [31:0] $end
  $upscope $end
 $upscope $end
$enddefinitions $end


#0
b00000000000000000000000000001010 #
b00000000000000000000000000000101 $
b0000 %
b00000000000000000000000000001111 &
#1000
b0001 %
b00000000000000000000000000000101 &
#2000
b0010 %
b00000000000000000000000000000000 &
#3000
b0011 %
b00000000000000000000000000001111 &
#4000
b0100 %
#5000
b0101 %
b00000000000000000000000101000000 &
#6000
b0110 %
b00000000000000000000000000000000 &
#7000
b11111111111111111111111111111011 #
b00000000000000000000000000000011 $
b0111 %
b00000000000000000000000000000001 &
#8000
b11111111111111111111111111111111 #
b00000000000000000000000000000001 $
b1000 %
b00000000000000000000000000000000 &
