rtl/regfile.sv
//regfile.sv
//register file, async reads and sync writes to register
`timescale 1ns/1ps
module regfile(
    input   logic           clk, // system clock
    input   logic           we, // write enable
    input   logic [4:0]     rs1, // register source 1
    input   logic [4:0]     rs2, 
    input   logic [4:0]     rd, // register destination
    input   logic [31:0]    wdata, // data to write

    output  logic [31:0]    rs1_data, // data from rs1
    output  logic [31:0]    rs2_data
);
    // 32 x 32-bit registers
    logic [31:0] regs [31:0];

    // async reads
    assign rs1_data = (rs1 == 0) ? 32'd0 : regs[rs1];
    assign rs2_data = (rs2 == 0) ? 32'd0 : regs[rs2];

    //sync writes
    always_ff @(posedge clk) begin 
        if (we && rd != 0)
            regs[rd] <= wdata;
    end

endmodule

tb/tb_regfile.sv
//tb_regfile.sv

`timescale 1ns/1ps

module tb_regfile;
    //inputs
    logic           clk; // system clock
    logic           we; // write enable
    logic [4:0]     rs1; // register source 1
    logic [4:0]     rs2; 
    logic [4:0]     rd; // register destination
    logic [31:0]    wdata; // data to write

    //outputs
    logic [31:0]    rs1_data; // data from rs1
    logic [31:0]    rs2_data;

    //instantiate regfile
    regfile uut (
        .clk(clk),
        .we(we),
        .rs1(rs1),
        .rs2(rs2),
        .rd(rd),
        .wdata(wdata),
        .rs1_data(rs1_data),
        .rs2_data(rs2_data)
    );

    initial begin
        $dumpfile("tb_regfile.vcd"); //name output vcd
        $dumpvars(0, tb_regfile); //dump everything recursively
    end

    //clock generation
    initial clk = 0;
    always #5 clk = ~clk; //changes every 5 ns, 10 ns period

    //testing
    initial begin
        $display("=== Register File Test ===");
        
        rs1 = 1; rs2 = 2; // reading from regs[1] and regs[2]. initially every element in regs is 0
        #1; //wait 1 time unit
        $display("Read x1 = %0d, x2= %0d. Expected x1 = x2 = 0.", rs1_data, rs2_data);

        // write 42 to x1
        rd = 1; wdata = 42; we = 1;
        #10; // wait one full cycle, ensuring a posedge happens
        we = 0; 
        #1;
        $display("After write: x1 = %0d, x2 = %0d. Expected x1 = 42, x2 = 0.", rs1_data, rs2_data);

        //try writing to x0, should remain 0
        rd = 0; wdata = 99; we = 1;
        #10; we = 0;
        #1;
        $display("After write: x0 = %0d. Expected always x0 = 0.", uut.regs[0]);

        //write 5 to x2
        rd = 2; wdata = 5; we = 1;
        #10; we = 0;
        rs1 = 1; rs2 = 2;
        #1;
        $display("After write: x1 = %0d, x2 = %0d. Expected x1 = 42, x2 = 5.", rs1_data, rs2_data);


        $display ("=== Register File Test Complete ===");
        $finish;
    end
endmodule

tb_regfile.vcd
$version Generated by VerilatedVcd $end
$timescale 1ps $end
 $scope module tb_regfile $end
  $var wire 1 H clk $end
  $var wire 1 # we $end
  $var wire 5 $ rs1 [4:0] $end
  $var wire 5 % rs2 [4:0] $end
  $var wire 5 & rd [4:0] $end
  $var wire 32 ' wdata [31:0] $end
  $var wire 32 I rs1_data [31:0] $end
  $var wire 32 J rs2_data [31:0] $end
  $scope module uut $end
   $var wire 1 H clk $end
   $var wire 1 # we $end
   $var wire 5 $ rs1 [4:0] $end
   $var wire 5 % rs2 [4:0] $end
   $var wire 5 & rd [4:0] $end
   $var wire 32 ' wdata [31:0] $end
   $var wire 32 I rs1_data [31:0] $end
   $var wire 32 J rs2_data [31:0] $end
   $var wire 32 ( regs[0] [31:0] $end
   $var wire 32 ) regs[1] [31:0] $end
   $var wire 32 * regs[2] [31:0] $end
   $var wire 32 + regs[3] [31:0] $end
   $var wire 32 , regs[4] [31:0] $end
   $var wire 32 - regs[5] [31:0] $end
   $var wire 32 . regs[6] [31:0] $end
   $var wire 32 / regs[7] [31:0] $end
   $var wire 32 0 regs[8] [31:0] $end
   $var wire 32 1 regs[9] [31:0] $end
   $var wire 32 2 regs[10] [31:0] $end
   $var wire 32 3 regs[11] [31:0] $end
   $var wire 32 4 regs[12] [31:0] $end
   $var wire 32 5 regs[13] [31:0] $end
   $var wire 32 6 regs[14] [31:0] $end
   $var wire 32 7 regs[15] [31:0] $end
   $var wire 32 8 regs[16] [31:0] $end
   $var wire 32 9 regs[17] [31:0] $end
   $var wire 32 : regs[18] [31:0] $end
   $var wire 32 ; regs[19] [31:0] $end
   $var wire 32 < regs[20] [31:0] $end
   $var wire 32 = regs[21] [31:0] $end
   $var wire 32 > regs[22] [31:0] $end
   $var wire 32 ? regs[23] [31:0] $end
   $var wire 32 @ regs[24] [31:0] $end
   $var wire 32 A regs[25] [31:0] $end
   $var wire 32 B regs[26] [31:0] $end
   $var wire 32 C regs[27] [31:0] $end
   $var wire 32 D regs[28] [31:0] $end
   $var wire 32 E regs[29] [31:0] $end
   $var wire 32 F regs[30] [31:0] $end
   $var wire 32 G regs[31] [31:0] $end
  $upscope $end
 $upscope $end
$enddefinitions $end


#0
0#
b00001 $
b00010 %
b00000 &
b00000000000000000000000000000000 '
b00000000000000000000000000000000 (
b00000000000000000000000000000000 )
b00000000000000000000000000000000 *
b00000000000000000000000000000000 +
b00000000000000000000000000000000 ,
b00000000000000000000000000000000 -
b00000000000000000000000000000000 .
b00000000000000000000000000000000 /
b00000000000000000000000000000000 0
b00000000000000000000000000000000 1
b00000000000000000000000000000000 2
b00000000000000000000000000000000 3
b00000000000000000000000000000000 4
b00000000000000000000000000000000 5
b00000000000000000000000000000000 6
b00000000000000000000000000000000 7
b00000000000000000000000000000000 8
b00000000000000000000000000000000 9
b00000000000000000000000000000000 :
b00000000000000000000000000000000 ;
b00000000000000000000000000000000 <
b00000000000000000000000000000000 =
b00000000000000000000000000000000 >
b00000000000000000000000000000000 ?
b00000000000000000000000000000000 @
b00000000000000000000000000000000 A
b00000000000000000000000000000000 B
b00000000000000000000000000000000 C
b00000000000000000000000000000000 D
b00000000000000000000000000000000 E
b00000000000000000000000000000000 F
b00000000000000000000000000000000 G
0H
b00000000000000000000000000000000 I
b00000000000000000000000000000000 J
#1000
1#
b00001 &
b00000000000000000000000000101010 '
#5000
b00000000000000000000000000101010 )
1H
b00000000000000000000000000101010 I
#10000
0H
#11000
0#
#12000
1#
b00000 &
b00000000000000000000000001100011 '
#15000
1H
#20000
0H
#22000
0#
#23000
1#
b00010 &
b00000000000000000000000000000101 '
#25000
b00000000000000000000000000000101 *
1H
b00000000000000000000000000000101 J
#30000
0H
#33000
0#
